location_app/__init__.py
location_app/admin.py
location_app/conf.py
location_app/forms.py
location_app/models.py
location_app/tests.py
location_app/urls.py
location_app/views.py
location_app/widgets.py
location_app/migrations/0001_initial.py
location_app/migrations/__init__.py
location_app/static/location_app/js/location.js
location_app/templates/location_app/location.html
django_location_app-1.0.4.dist-info/LICENSE
django_location_app-1.0.4.dist-info/METADATA
django_location_app-1.0.4.dist-info/WHEEL
django_location_app-1.0.4.dist-info/top_level.txt
django_location_app-1.0.4.dist-info/RECORD
