Metadata-Version: 2.1
Name: django-location-app
Version: 1.0.4
Summary: A Django app that helps you easily manage your own location data with autocomplete function. Connect your app to a completely normalized location database, avoid redundant Google Map API queries and save your hard earned money.
Home-page: https://github.com/AnmolChachra/django-location-app
Author: Anmol Chachra
Author-email: anmol.chachra@gmail.com
License: MIT
Project-URL: Funding, https://donate.pypi.org
Project-URL: Say Thanks!, https://saythanks.io/to/anmol.chachra@gmail.com
Project-URL: Source, https://github.com/AnmolChachra/django-location-app/
Project-URL: Tracker, https://github.com/AnmolChachra/django-location-app/issues
Keywords: django geocomplete google maps places
Platform: UNKNOWN
Classifier: Environment :: Web Environment
Classifier: License :: OSI Approved :: MIT License
Classifier: Operating System :: OS Independent
Classifier: Intended Audience :: Developers
Classifier: Framework :: Django
Classifier: Natural Language :: English
Classifier: Programming Language :: Python
Classifier: Programming Language :: Python :: 3
Requires-Python: >=3.7
Requires-Dist: Django (>=3.0)
